apies/VERSION
apies/__init__.py
apies/blueprint.py
apies/controllers.py
apies/logger.py
apies/query.py
apies/sources.py
apies/utils/__init__.py
apies/utils/file_maker.py
apisql/VERSION
apisql/__init__.py
apisql/blueprint.py
apisql/controllers.py
apisql/logger.py
apisql/utils/__init__.py
apisql/utils/file_maker.py
apisql-0.7.4.dist-info/LICENSE
apisql-0.7.4.dist-info/METADATA
apisql-0.7.4.dist-info/WHEEL
apisql-0.7.4.dist-info/top_level.txt
apisql-0.7.4.dist-info/RECORD
