Metadata-Version: 2.1
Name: apisql
Version: 0.7.4
Summary: A flask blueprint providing a read-lny API for querying RDBMS
Home-page: https://github.com/dataspot/apisql
Author: Adam Kariv
Author-email: adam.kariv@gmail.com
License: MIT
Keywords: data
Classifier: Development Status :: 4 - Beta
Classifier: Intended Audience :: Developers
Classifier: License :: OSI Approved :: MIT License
Classifier: Operating System :: OS Independent
Classifier: Programming Language :: Python :: 3.6
Classifier: Topic :: Software Development :: Libraries :: Python Modules
License-File: LICENSE
Requires-Dist: psycopg2-binary
Requires-Dist: flask-jsonpify
Requires-Dist: openpyxl
Requires-Dist: backports.cached-property
Provides-Extra: develop
Requires-Dist: pylama ; extra == 'develop'
Requires-Dist: tox ; extra == 'develop'
